sodym/__init__.py
sodym/classes/__init__.py
sodym/classes/dimensions.py
sodym/classes/dynamic_stock_model.py
sodym/classes/mfa_system.py
sodym/classes/named_dim_arrays.py
sodym/classes/stocks_in_mfa.py
sodym/tools/__init__.py
sodym/tools/config.py
sodym/tools/export.py
sodym/tools/paths.py
sodym/tools/read_data.py
sodym/tools/tools.py
sodym/tools/visualize/__init__.py
sodym/tools/visualize/plot_array.py
sodym/tools/visualize/sankey.py
sodym-0.1.0.dist-info/LICENSE
sodym-0.1.0.dist-info/METADATA
sodym-0.1.0.dist-info/WHEEL
sodym-0.1.0.dist-info/RECORD
