Metadata-Version: 2.1
Name: sodym
Version: 0.1.0
Summary: 
Author: Jakob Dürrwächter, Merlin Hosak, Stefan Pauliuk
Requires-Python: >=3.10,<3.13
Classifier: Programming Language :: Python :: 3
Classifier: Programming Language :: Python :: 3.10
Classifier: Programming Language :: Python :: 3.11
Classifier: Programming Language :: Python :: 3.12
Requires-Dist: PyYAML (>=6.0,<7.0)
Requires-Dist: matplotlib (>=3.7.1,<4.0.0)
Requires-Dist: numpy (>=1.25.0,<2.0.0)
Requires-Dist: pandas (>=2.0.2,<3.0.0)
Requires-Dist: pickle4 (>=0.0.1,<0.0.2)
Requires-Dist: plotly (>=5.18.0,<6.0.0)
Requires-Dist: scipy (>=1.11.0,<2.0.0)
